markdrop/__init__.py
markdrop/helper.py
markdrop/ignore_warnings.py
markdrop/main.py
markdrop/parse.py
markdrop/process.py
markdrop/run.py
markdrop/setup_keys.py
markdrop/utils.py
markdrop/models/__init__.py
markdrop/models/img_descriptions.py
markdrop/models/logger.py
markdrop/models/model_loader.py
markdrop/models/responder.py
markdrop-3.5.0.dist-info/licenses/LICENSE
markdrop-3.5.0.dist-info/METADATA
markdrop-3.5.0.dist-info/WHEEL
markdrop-3.5.0.dist-info/entry_points.txt
markdrop-3.5.0.dist-info/top_level.txt
markdrop-3.5.0.dist-info/RECORD
