Metadata-Version: 2.4
Name: markdrop
Version: 3.5.0
Summary: A comprehensive PDF processing toolkit that converts PDFs to markdown with advanced AI-powered features for image and table analysis. Supports local files and URLs, preserves document structure, extracts high-quality images, detects tables using advanced ML models, and generates detailed content descriptions using multiple LLM providers including OpenAI and Google's Gemini.
Home-page: https://github.com/shoryasethia/markdrop
Author: Shorya Sethia
Author-email: shoryasethia4may@gmail.com
Keywords: pdf markdown converter ai llm table-extraction image-analysis document-processing gemini openai
Classifier: Programming Language :: Python :: 3
Classifier: License :: OSI Approved :: MIT License
Classifier: Operating System :: OS Independent
Classifier: Development Status :: 4 - Beta
Classifier: Intended Audience :: Developers
Classifier: Intended Audience :: Science/Research
Classifier: Topic :: Scientific/Engineering :: Artificial Intelligence
Classifier: Topic :: Text Processing :: Markup :: Markdown
Classifier: Topic :: Software Development :: Libraries :: Python Modules
Requires-Python: >=3.10
License-File: LICENSE
Requires-Dist: beautifulsoup4
Requires-Dist: docling
Requires-Dist: docling_core==2.16.0
Requires-Dist: openai
Requires-Dist: openpyxl
Requires-Dist: pandas
Requires-Dist: Pillow
Requires-Dist: protobuf
Requires-Dist: python-dotenv
Requires-Dist: pymupdf
Requires-Dist: requests
Requires-Dist: google-generativeai
Requires-Dist: numpy<2.0
Dynamic: author
Dynamic: author-email
Dynamic: classifier
Dynamic: description
Dynamic: description-content-type
Dynamic: home-page
Dynamic: keywords
Dynamic: license-file
Dynamic: requires-dist
Dynamic: requires-python
Dynamic: summary
